duckguard/__init__.py
duckguard/errors.py
duckguard/anomaly/__init__.py
duckguard/anomaly/baselines.py
duckguard/anomaly/detector.py
duckguard/anomaly/methods.py
duckguard/anomaly/ml_methods.py
duckguard/checks/__init__.py
duckguard/checks/conditional.py
duckguard/checks/distributional.py
duckguard/checks/multicolumn.py
duckguard/checks/query_based.py
duckguard/cli/__init__.py
duckguard/cli/main.py
duckguard/connectors/__init__.py
duckguard/connectors/base.py
duckguard/connectors/bigquery.py
duckguard/connectors/databricks.py
duckguard/connectors/factory.py
duckguard/connectors/files.py
duckguard/connectors/kafka.py
duckguard/connectors/mongodb.py
duckguard/connectors/mysql.py
duckguard/connectors/oracle.py
duckguard/connectors/postgres.py
duckguard/connectors/redshift.py
duckguard/connectors/snowflake.py
duckguard/connectors/sqlite.py
duckguard/connectors/sqlserver.py
duckguard/contracts/__init__.py
duckguard/contracts/diff.py
duckguard/contracts/generator.py
duckguard/contracts/loader.py
duckguard/contracts/schema.py
duckguard/contracts/validator.py
duckguard/core/__init__.py
duckguard/core/column.py
duckguard/core/dataset.py
duckguard/core/engine.py
duckguard/core/result.py
duckguard/core/scoring.py
duckguard/freshness/__init__.py
duckguard/freshness/monitor.py
duckguard/history/__init__.py
duckguard/history/schema.py
duckguard/history/storage.py
duckguard/history/trends.py
duckguard/integrations/__init__.py
duckguard/integrations/airflow.py
duckguard/integrations/dbt.py
duckguard/notifications/__init__.py
duckguard/notifications/email.py
duckguard/notifications/formatter.py
duckguard/notifications/notifiers.py
duckguard/profiler/__init__.py
duckguard/profiler/auto_profile.py
duckguard/profiler/distribution_analyzer.py
duckguard/profiler/outlier_detector.py
duckguard/profiler/pattern_matcher.py
duckguard/profiler/quality_scorer.py
duckguard/pytest_plugin/__init__.py
duckguard/pytest_plugin/plugin.py
duckguard/reporting/__init__.py
duckguard/reporting/console.py
duckguard-3.1.0.dist-info/METADATA
duckguard-3.1.0.dist-info/WHEEL
duckguard-3.1.0.dist-info/entry_points.txt
duckguard-3.1.0.dist-info/licenses/LICENSE
duckguard-3.1.0.dist-info/RECORD
