Metadata-Version: 2.4
Name: duckguard
Version: 3.1.0
Summary: A Python-native data quality tool with AI superpowers, built on DuckDB for speed
Project-URL: Homepage, https://github.com/XDataHubAI/duckguard
Project-URL: Documentation, https://github.com/XDataHubAI/duckguard
Project-URL: Repository, https://github.com/XDataHubAI/duckguard
Author: DuckGuard Team
License-Expression: Elastic-2.0
License-File: LICENSE
Keywords: airflow,anomaly-detection,data-catalog,data-contracts,data-engineering,data-governance,data-lineage,data-observability,data-pipeline,data-profiling,data-quality,data-testing,data-validation,dbt,duckdb,etl,great-expectations,pii-detection,pytest-plugin,schema-validation,soda,testing
Classifier: Development Status :: 4 - Beta
Classifier: Environment :: Console
Classifier: Framework :: Pytest
Classifier: Intended Audience :: Developers
Classifier: Intended Audience :: Information Technology
Classifier: Intended Audience :: Science/Research
Classifier: License :: Other/Proprietary License
Classifier: Operating System :: OS Independent
Classifier: Programming Language :: Python :: 3
Classifier: Programming Language :: Python :: 3.10
Classifier: Programming Language :: Python :: 3.11
Classifier: Programming Language :: Python :: 3.12
Classifier: Topic :: Database
Classifier: Topic :: Scientific/Engineering :: Information Analysis
Classifier: Topic :: Software Development :: Quality Assurance
Classifier: Topic :: Software Development :: Testing
Classifier: Typing :: Typed
Requires-Python: >=3.10
Requires-Dist: duckdb>=1.0.0
Requires-Dist: packaging>=21.0
Requires-Dist: pyarrow>=14.0.0
Requires-Dist: pydantic>=2.0.0
Requires-Dist: pyyaml>=6.0.0
Requires-Dist: rich>=13.0.0
Requires-Dist: typer>=0.9.0
Provides-Extra: airflow
Requires-Dist: apache-airflow>=2.5.0; extra == 'airflow'
Provides-Extra: all
Requires-Dist: anthropic>=0.18.0; extra == 'all'
Requires-Dist: apache-airflow>=2.5.0; extra == 'all'
Requires-Dist: databricks-sql-connector>=2.0.0; extra == 'all'
Requires-Dist: google-cloud-bigquery>=3.0.0; extra == 'all'
Requires-Dist: jinja2>=3.0.0; extra == 'all'
Requires-Dist: kafka-python>=2.0.0; extra == 'all'
Requires-Dist: openai>=1.0.0; extra == 'all'
Requires-Dist: oracledb>=1.0.0; extra == 'all'
Requires-Dist: psycopg2-binary>=2.9.0; extra == 'all'
Requires-Dist: pymongo>=4.0.0; extra == 'all'
Requires-Dist: pymysql>=1.0.0; extra == 'all'
Requires-Dist: pyodbc>=4.0.0; extra == 'all'
Requires-Dist: redshift-connector>=2.0.0; extra == 'all'
Requires-Dist: scipy>=1.11.0; extra == 'all'
Requires-Dist: snowflake-connector-python>=3.0.0; extra == 'all'
Requires-Dist: weasyprint>=60.0; extra == 'all'
Provides-Extra: bigquery
Requires-Dist: google-cloud-bigquery>=3.0.0; extra == 'bigquery'
Provides-Extra: databases
Requires-Dist: databricks-sql-connector>=2.0.0; extra == 'databases'
Requires-Dist: google-cloud-bigquery>=3.0.0; extra == 'databases'
Requires-Dist: kafka-python>=2.0.0; extra == 'databases'
Requires-Dist: oracledb>=1.0.0; extra == 'databases'
Requires-Dist: psycopg2-binary>=2.9.0; extra == 'databases'
Requires-Dist: pymongo>=4.0.0; extra == 'databases'
Requires-Dist: pymysql>=1.0.0; extra == 'databases'
Requires-Dist: pyodbc>=4.0.0; extra == 'databases'
Requires-Dist: redshift-connector>=2.0.0; extra == 'databases'
Requires-Dist: snowflake-connector-python>=3.0.0; extra == 'databases'
Provides-Extra: databricks
Requires-Dist: databricks-sql-connector>=2.0.0; extra == 'databricks'
Provides-Extra: dev
Requires-Dist: black>=23.0.0; extra == 'dev'
Requires-Dist: mypy>=1.0.0; extra == 'dev'
Requires-Dist: numpy>=1.24.0; extra == 'dev'
Requires-Dist: pandas>=2.0.0; extra == 'dev'
Requires-Dist: psutil>=5.9.0; extra == 'dev'
Requires-Dist: pytest-cov>=4.0.0; extra == 'dev'
Requires-Dist: pytest>=7.0.0; extra == 'dev'
Requires-Dist: ruff>=0.1.0; extra == 'dev'
Requires-Dist: scipy>=1.11.0; extra == 'dev'
Provides-Extra: kafka
Requires-Dist: kafka-python>=2.0.0; extra == 'kafka'
Provides-Extra: llm
Requires-Dist: anthropic>=0.18.0; extra == 'llm'
Requires-Dist: openai>=1.0.0; extra == 'llm'
Provides-Extra: mongodb
Requires-Dist: pymongo>=4.0.0; extra == 'mongodb'
Provides-Extra: mysql
Requires-Dist: pymysql>=1.0.0; extra == 'mysql'
Provides-Extra: oracle
Requires-Dist: oracledb>=1.0.0; extra == 'oracle'
Provides-Extra: postgres
Requires-Dist: psycopg2-binary>=2.9.0; extra == 'postgres'
Provides-Extra: redshift
Requires-Dist: redshift-connector>=2.0.0; extra == 'redshift'
Provides-Extra: reports
Requires-Dist: jinja2>=3.0.0; extra == 'reports'
Requires-Dist: weasyprint>=60.0; extra == 'reports'
Provides-Extra: snowflake
Requires-Dist: snowflake-connector-python>=3.0.0; extra == 'snowflake'
Provides-Extra: sqlserver
Requires-Dist: pyodbc>=4.0.0; extra == 'sqlserver'
Provides-Extra: statistics
Requires-Dist: scipy>=1.11.0; extra == 'statistics'
